repeatbot/__init__.py
repeatbot/common.py
repeatbot/recorder.py
repeatbot/repeater.py
repeatbot-0.2.dist-info/LICENSE.txt
repeatbot-0.2.dist-info/METADATA
repeatbot-0.2.dist-info/WHEEL
repeatbot-0.2.dist-info/top_level.txt
repeatbot-0.2.dist-info/RECORD
