Metadata-Version: 2.1
Name: repeatbot
Version: 0.2
Summary: Record, save and repeat mouse and keyboard inputs using pynput.
Home-page: https://github.com/StroppaFR/repeatbot
Author: Nicolas Stroppa
Author-email: 34066091+StroppaFR@users.noreply.github.com
Project-URL: Bug Tracker, https://github.com/StroppaFR/repeatbot/issues
Classifier: Programming Language :: Python :: 3
Classifier: License :: OSI Approved :: MIT License
Requires-Python: >=3.6
License-File: LICENSE.txt
